delver/__init__.py
delver/core.py
delver/delve.py
delver/exceptions.py
delver/handlers.py
delver/table.py
pydelver-0.0.6.dist-info/entry_points.txt
pydelver-0.0.6.dist-info/LICENSE
pydelver-0.0.6.dist-info/WHEEL
pydelver-0.0.6.dist-info/METADATA
pydelver-0.0.6.dist-info/RECORD
