Metadata-Version: 2.1
Name: pydelver
Version: 0.0.6
Summary: Helpful tool for stepping through nested objects
Home-page: https://github.com/NarrativeScience/delver
License: BSD-3-Clause
Keywords: data,command line tools,json
Author: Alex Sippel
Author-email: asippel@narrativescience.com
Requires-Python: >=3.6,<4
Classifier: Intended Audience :: Developers
Classifier: License :: OSI Approved :: BSD License
Classifier: Programming Language :: Python :: 3
Classifier: Programming Language :: Python :: 2
Classifier: Topic :: Software Development :: Libraries :: Python Modules
Requires-Dist: colorful>=0.4.0
Requires-Dist: six>=1.10.0
Requires-Dist: terminaltables>=3.1.0
